{
    "timestamp": 1737668399,
    "result": {
        "lakeName": "Little Johanna",
        "sampledPlants": [],
        "shoreLengthMiles": 0.7,
        "DOWNumber": 62005800,
        "waterClarity": [],
        "averageWaterClarity": "N/A",
        "littoralAcres": 12.0,
        "areaAcres": 17.17,
        "meanDepthFeet": 0.0,
        "maxDepthFeet": 28.0,
        "officeCode": "F313",
        "accesses": [
            {
                "location": "NONE",
                "ownerTypeID": null,
                "accessTypeID": null,
                "publicUseAuthCode": "UNK",
                "lakeAccessComments": " "
            }
        ],
        "surveys": [
            {
                "surveyID": "120020",
                "fishCatchSummaries": [
                    {
                        "CPUE": "2.00",
                        "quartileCount": "2.5-7.9",
                        "totalWeight": 3.0,
                        "gearCount": 1.0,
                        "quartileWeight": "1.8-3.3",
                        "species": "NOP",
                        "gear": "Standard gill nets",
                        "averageWeight": "1.50",
                        "totalCatch": 2
                    },
                    {
                        "CPUE": "19.00",
                        "quartileCount": "1.9-18.0",
                        "totalWeight": 2.9,
                        "gearCount": 1.0,
                        "quartileWeight": "0.1-0.3",
                        "species": "BLC",
                        "gear": "Standard gill nets",
                        "averageWeight": "0.15",
                        "totalCatch": 19
                    },
                    {
                        "CPUE": "14.00",
                        "quartileCount": "5.2-56.2",
                        "totalWeight": 1.0,
                        "gearCount": 1.0,
                        "quartileWeight": "0.2-0.5",
                        "species": "BLB",
                        "gear": "Standard gill nets",
                        "averageWeight": "0.07",
                        "totalCatch": 14
                    },
                    {
                        "CPUE": "1.00",
                        "quartileCount": "0.7-6.2",
                        "totalWeight": 0.1,
                        "gearCount": 1.0,
                        "quartileWeight": "0.2-0.6",
                        "species": "BRB",
                        "gear": "Standard gill nets",
                        "averageWeight": "0.10",
                        "totalCatch": 1
                    },
                    {
                        "CPUE": "14.00",
                        "quartileCount": "0.5-4.0",
                        "totalWeight": 20.5,
                        "gearCount": 1.0,
                        "quartileWeight": "1.0-3.2",
                        "species": "CAP",
                        "gear": "Standard gill nets",
                        "averageWeight": "1.46",
                        "totalCatch": 14
                    }
                ],
                "narrative": "<p>BASED ON THE GILLNET CATCH ONLY, CARP, BLACK BULLHEAD, AND BLACK CRAPPIES WERE FOUND AT ABOVE LOCAL MEDIAN LEVELS. BROWN BULLHEAD AND NORTHERN PIKE WERE SAMPLED AT BELOW LOCAL MEDIAN LEVELS. YELLOW BULLHEAD, LARGEMOUTH BASS, GREEN SUNFISH, PUMPKINSEED, BLUEGILL AND HYBRID SUNFISH ARE KNOWN TO INHABIT THE LAKE FROM THE 1979 TEST NETTTING, AND 1/4</p>",
                "headerInfo": [
                    "Little Johanna",
                    null,
                    "62005800",
                    "1984-08-06",
                    "120020",
                    "Initial Survey"
                ],
                "surveyType": "Standard Survey",
                "surveySubType": "Initial Survey",
                "surveyDate": "1984-08-06",
                "lengths": {}
            },
            {
                "surveyID": "119924",
                "fishCatchSummaries": [
                    {
                        "CPUE": "18.00",
                        "quartileCount": "1.9-18.0",
                        "totalWeight": 6.75,
                        "gearCount": 1.0,
                        "quartileWeight": "0.1-0.3",
                        "species": "BLC",
                        "gear": "Standard gill nets",
                        "averageWeight": "0.38",
                        "totalCatch": 18
                    },
                    {
                        "CPUE": "15.00",
                        "quartileCount": "5.2-56.2",
                        "totalWeight": 3.25,
                        "gearCount": 1.0,
                        "quartileWeight": "0.2-0.5",
                        "species": "BLB",
                        "gear": "Standard gill nets",
                        "averageWeight": "0.22",
                        "totalCatch": 15
                    },
                    {
                        "CPUE": "10.00",
                        "quartileCount": "0.7-6.2",
                        "totalWeight": 5.5,
                        "gearCount": 1.0,
                        "quartileWeight": "0.2-0.6",
                        "species": "BRB",
                        "gear": "Standard gill nets",
                        "averageWeight": "0.55",
                        "totalCatch": 10
                    },
                    {
                        "CPUE": "2.00",
                        "quartileCount": "N/A",
                        "totalWeight": 0.2,
                        "gearCount": 1.0,
                        "quartileWeight": "N/A",
                        "species": "PMK",
                        "gear": "Standard gill nets",
                        "averageWeight": "0.10",
                        "totalCatch": 2
                    },
                    {
                        "CPUE": "2.00",
                        "quartileCount": "1.0-6.9",
                        "totalWeight": 0.75,
                        "gearCount": 1.0,
                        "quartileWeight": "0.4-0.7",
                        "species": "YEB",
                        "gear": "Standard gill nets",
                        "averageWeight": "0.38",
                        "totalCatch": 2
                    },
                    {
                        "CPUE": "2.00",
                        "quartileCount": "0.3-1.1",
                        "totalWeight": 0.75,
                        "gearCount": 1.0,
                        "quartileWeight": "0.4-1.5",
                        "species": "LMB",
                        "gear": "Standard gill nets",
                        "averageWeight": "0.38",
                        "totalCatch": 2
                    },
                    {
                        "CPUE": "29.00",
                        "quartileCount": "N/A",
                        "totalWeight": 8.75,
                        "gearCount": 1.0,
                        "quartileWeight": "N/A",
                        "species": "BLG",
                        "gear": "Standard gill nets",
                        "averageWeight": "0.30",
                        "totalCatch": 29
                    }
                ],
                "narrative": "<p>Based on gill net catch only.  All species taken were in numbers per set above the local median. The Blk, Brn, and Yel Bullhead were each rprsntd by large individuals primarily.  Over 70% of the Bluegill taken were fish 6.5 inches or larger. The Blk Crappie taken were also larger fish with 10 of 18 being 8.0 inches or larger.</p>",
                "headerInfo": [
                    "Little Johanna",
                    null,
                    "62005800",
                    "1979-08-07",
                    "119924",
                    "Population Assessment"
                ],
                "surveyType": "Standard Survey",
                "surveySubType": "Population Assessment",
                "surveyDate": "1979-08-07",
                "lengths": {}
            }
        ],
        "countyName": "Ramsey"
    },
    "status": "SUCCESS",
    "message": "Normal execution."
}